{
  "image_id": 4517,
  "image_path": "images/image_004517.png",
  "num_objects": 3,
  "objects": [
    {
      "shape": "circle",
      "color": [
        0,
        0,
        255
      ],
      "bbox": [
        15,
        5,
        28,
        18
      ],
      "center": [
        21,
        11
      ],
      "size": [
        13,
        13
      ],
      "area": 169
    },
    {
      "shape": "circle",
      "color": [
        128,
        0,
        255
      ],
      "bbox": [
        39,
        21,
        59,
        41
      ],
      "center": [
        49,
        31
      ],
      "size": [
        20,
        20
      ],
      "area": 400
    },
    {
      "shape": "circle",
      "color": [
        255,
        128,
        0
      ],
      "bbox": [
        43,
        16,
        54,
        27
      ],
      "center": [
        48,
        21
      ],
      "size": [
        11,
        11
      ],
      "area": 121
    }
  ]
}