{
  "image_id": 2693,
  "image_path": "images/image_002693.png",
  "num_objects": 3,
  "objects": [
    {
      "shape": "triangle",
      "color": [
        128,
        0,
        255
      ],
      "bbox": [
        38,
        23,
        48,
        33
      ],
      "center": [
        43,
        28
      ],
      "size": [
        10,
        10
      ],
      "area": 100
    },
    {
      "shape": "circle",
      "color": [
        0,
        255,
        255
      ],
      "bbox": [
        9,
        37,
        20,
        48
      ],
      "center": [
        14,
        42
      ],
      "size": [
        11,
        11
      ],
      "area": 121
    },
    {
      "shape": "triangle",
      "color": [
        255,
        0,
        255
      ],
      "bbox": [
        1,
        7,
        19,
        25
      ],
      "center": [
        10,
        16
      ],
      "size": [
        18,
        18
      ],
      "area": 324
    }
  ]
}