{
  "image_id": 2493,
  "image_path": "images/image_002493.png",
  "num_objects": 4,
  "objects": [
    {
      "shape": "triangle",
      "color": [
        128,
        0,
        255
      ],
      "bbox": [
        53,
        10,
        63,
        20
      ],
      "center": [
        58,
        15
      ],
      "size": [
        10,
        10
      ],
      "area": 100
    },
    {
      "shape": "circle",
      "color": [
        0,
        255,
        0
      ],
      "bbox": [
        24,
        19,
        39,
        34
      ],
      "center": [
        31,
        26
      ],
      "size": [
        15,
        15
      ],
      "area": 225
    },
    {
      "shape": "circle",
      "color": [
        128,
        0,
        255
      ],
      "bbox": [
        11,
        14,
        21,
        24
      ],
      "center": [
        16,
        19
      ],
      "size": [
        10,
        10
      ],
      "area": 100
    },
    {
      "shape": "square",
      "color": [
        255,
        255,
        0
      ],
      "bbox": [
        6,
        43,
        27,
        64
      ],
      "center": [
        16,
        53
      ],
      "size": [
        21,
        21
      ],
      "area": 441
    }
  ]
}