{
  "image_id": 3085,
  "image_path": "images/image_003085.png",
  "num_objects": 4,
  "objects": [
    {
      "shape": "circle",
      "color": [
        0,
        0,
        255
      ],
      "bbox": [
        23,
        3,
        32,
        12
      ],
      "center": [
        27,
        7
      ],
      "size": [
        9,
        9
      ],
      "area": 81
    },
    {
      "shape": "triangle",
      "color": [
        255,
        0,
        255
      ],
      "bbox": [
        11,
        13,
        27,
        29
      ],
      "center": [
        19,
        21
      ],
      "size": [
        16,
        16
      ],
      "area": 256
    },
    {
      "shape": "circle",
      "color": [
        0,
        0,
        255
      ],
      "bbox": [
        43,
        12,
        64,
        33
      ],
      "center": [
        53,
        22
      ],
      "size": [
        21,
        21
      ],
      "area": 441
    },
    {
      "shape": "square",
      "color": [
        255,
        128,
        0
      ],
      "bbox": [
        18,
        9,
        30,
        21
      ],
      "center": [
        24,
        15
      ],
      "size": [
        12,
        12
      ],
      "area": 144
    }
  ]
}