{
  "image_id": 6806,
  "image_path": "images/image_006806.png",
  "num_objects": 4,
  "objects": [
    {
      "shape": "square",
      "color": [
        255,
        128,
        0
      ],
      "bbox": [
        45,
        43,
        63,
        61
      ],
      "center": [
        54,
        52
      ],
      "size": [
        18,
        18
      ],
      "area": 324
    },
    {
      "shape": "square",
      "color": [
        0,
        255,
        255
      ],
      "bbox": [
        38,
        44,
        54,
        60
      ],
      "center": [
        46,
        52
      ],
      "size": [
        16,
        16
      ],
      "area": 256
    },
    {
      "shape": "square",
      "color": [
        255,
        255,
        0
      ],
      "bbox": [
        23,
        0,
        33,
        10
      ],
      "center": [
        28,
        5
      ],
      "size": [
        10,
        10
      ],
      "area": 100
    },
    {
      "shape": "circle",
      "color": [
        255,
        128,
        0
      ],
      "bbox": [
        41,
        22,
        53,
        34
      ],
      "center": [
        47,
        28
      ],
      "size": [
        12,
        12
      ],
      "area": 144
    }
  ]
}