{
  "image_id": 5394,
  "image_path": "images/image_005394.png",
  "num_objects": 3,
  "objects": [
    {
      "shape": "triangle",
      "color": [
        255,
        0,
        0
      ],
      "bbox": [
        47,
        28,
        64,
        45
      ],
      "center": [
        55,
        36
      ],
      "size": [
        17,
        17
      ],
      "area": 289
    },
    {
      "shape": "square",
      "color": [
        0,
        0,
        255
      ],
      "bbox": [
        14,
        42,
        35,
        63
      ],
      "center": [
        24,
        52
      ],
      "size": [
        21,
        21
      ],
      "area": 441
    },
    {
      "shape": "triangle",
      "color": [
        128,
        0,
        255
      ],
      "bbox": [
        26,
        7,
        35,
        16
      ],
      "center": [
        30,
        11
      ],
      "size": [
        9,
        9
      ],
      "area": 81
    }
  ]
}