{
  "image_id": 2853,
  "image_path": "images/image_002853.png",
  "num_objects": 4,
  "objects": [
    {
      "shape": "square",
      "color": [
        255,
        0,
        0
      ],
      "bbox": [
        6,
        25,
        27,
        46
      ],
      "center": [
        16,
        35
      ],
      "size": [
        21,
        21
      ],
      "area": 441
    },
    {
      "shape": "square",
      "color": [
        0,
        0,
        255
      ],
      "bbox": [
        38,
        40,
        54,
        56
      ],
      "center": [
        46,
        48
      ],
      "size": [
        16,
        16
      ],
      "area": 256
    },
    {
      "shape": "circle",
      "color": [
        0,
        255,
        255
      ],
      "bbox": [
        40,
        48,
        54,
        62
      ],
      "center": [
        47,
        55
      ],
      "size": [
        14,
        14
      ],
      "area": 196
    },
    {
      "shape": "square",
      "color": [
        255,
        0,
        0
      ],
      "bbox": [
        11,
        25,
        21,
        35
      ],
      "center": [
        16,
        30
      ],
      "size": [
        10,
        10
      ],
      "area": 100
    }
  ]
}