{
  "image_id": 6867,
  "image_path": "images/image_006867.png",
  "num_objects": 4,
  "objects": [
    {
      "shape": "circle",
      "color": [
        0,
        0,
        255
      ],
      "bbox": [
        30,
        17,
        41,
        28
      ],
      "center": [
        35,
        22
      ],
      "size": [
        11,
        11
      ],
      "area": 121
    },
    {
      "shape": "triangle",
      "color": [
        0,
        255,
        255
      ],
      "bbox": [
        47,
        7,
        62,
        22
      ],
      "center": [
        54,
        14
      ],
      "size": [
        15,
        15
      ],
      "area": 225
    },
    {
      "shape": "square",
      "color": [
        0,
        0,
        255
      ],
      "bbox": [
        3,
        42,
        24,
        63
      ],
      "center": [
        13,
        52
      ],
      "size": [
        21,
        21
      ],
      "area": 441
    },
    {
      "shape": "square",
      "color": [
        0,
        255,
        0
      ],
      "bbox": [
        32,
        26,
        54,
        48
      ],
      "center": [
        43,
        37
      ],
      "size": [
        22,
        22
      ],
      "area": 484
    }
  ]
}