{
  "image_id": 7329,
  "image_path": "images/image_007329.png",
  "num_objects": 4,
  "objects": [
    {
      "shape": "triangle",
      "color": [
        128,
        0,
        255
      ],
      "bbox": [
        15,
        24,
        35,
        44
      ],
      "center": [
        25,
        34
      ],
      "size": [
        20,
        20
      ],
      "area": 400
    },
    {
      "shape": "circle",
      "color": [
        0,
        0,
        255
      ],
      "bbox": [
        8,
        37,
        22,
        51
      ],
      "center": [
        15,
        44
      ],
      "size": [
        14,
        14
      ],
      "area": 196
    },
    {
      "shape": "square",
      "color": [
        255,
        0,
        0
      ],
      "bbox": [
        33,
        26,
        50,
        43
      ],
      "center": [
        41,
        34
      ],
      "size": [
        17,
        17
      ],
      "area": 289
    },
    {
      "shape": "triangle",
      "color": [
        128,
        0,
        255
      ],
      "bbox": [
        0,
        44,
        20,
        64
      ],
      "center": [
        10,
        54
      ],
      "size": [
        20,
        20
      ],
      "area": 400
    }
  ]
}