{
  "image_id": 7259,
  "image_path": "images/image_007259.png",
  "num_objects": 3,
  "objects": [
    {
      "shape": "square",
      "color": [
        0,
        0,
        255
      ],
      "bbox": [
        31,
        15,
        48,
        32
      ],
      "center": [
        39,
        23
      ],
      "size": [
        17,
        17
      ],
      "area": 289
    },
    {
      "shape": "circle",
      "color": [
        255,
        128,
        0
      ],
      "bbox": [
        11,
        18,
        32,
        39
      ],
      "center": [
        21,
        28
      ],
      "size": [
        21,
        21
      ],
      "area": 441
    },
    {
      "shape": "triangle",
      "color": [
        255,
        0,
        0
      ],
      "bbox": [
        26,
        0,
        39,
        13
      ],
      "center": [
        32,
        6
      ],
      "size": [
        13,
        13
      ],
      "area": 169
    }
  ]
}