{
  "image_id": 458,
  "image_path": "images/image_000458.png",
  "num_objects": 3,
  "objects": [
    {
      "shape": "square",
      "color": [
        255,
        128,
        0
      ],
      "bbox": [
        37,
        29,
        58,
        50
      ],
      "center": [
        47,
        39
      ],
      "size": [
        21,
        21
      ],
      "area": 441
    },
    {
      "shape": "triangle",
      "color": [
        0,
        255,
        0
      ],
      "bbox": [
        6,
        21,
        18,
        33
      ],
      "center": [
        12,
        27
      ],
      "size": [
        12,
        12
      ],
      "area": 144
    },
    {
      "shape": "square",
      "color": [
        255,
        0,
        255
      ],
      "bbox": [
        21,
        14,
        30,
        23
      ],
      "center": [
        25,
        18
      ],
      "size": [
        9,
        9
      ],
      "area": 81
    }
  ]
}