{
  "image_id": 5994,
  "image_path": "images/image_005994.png",
  "num_objects": 3,
  "objects": [
    {
      "shape": "circle",
      "color": [
        255,
        0,
        255
      ],
      "bbox": [
        28,
        22,
        38,
        32
      ],
      "center": [
        33,
        27
      ],
      "size": [
        10,
        10
      ],
      "area": 100
    },
    {
      "shape": "square",
      "color": [
        255,
        255,
        0
      ],
      "bbox": [
        42,
        25,
        63,
        46
      ],
      "center": [
        52,
        35
      ],
      "size": [
        21,
        21
      ],
      "area": 441
    },
    {
      "shape": "triangle",
      "color": [
        255,
        0,
        0
      ],
      "bbox": [
        25,
        30,
        34,
        39
      ],
      "center": [
        29,
        34
      ],
      "size": [
        9,
        9
      ],
      "area": 81
    }
  ]
}