{
  "image_id": 5804,
  "image_path": "images/image_005804.png",
  "num_objects": 2,
  "objects": [
    {
      "shape": "square",
      "color": [
        255,
        255,
        0
      ],
      "bbox": [
        9,
        12,
        22,
        25
      ],
      "center": [
        15,
        18
      ],
      "size": [
        13,
        13
      ],
      "area": 169
    },
    {
      "shape": "triangle",
      "color": [
        255,
        0,
        0
      ],
      "bbox": [
        19,
        40,
        37,
        58
      ],
      "center": [
        28,
        49
      ],
      "size": [
        18,
        18
      ],
      "area": 324
    }
  ]
}