{
  "image_id": 2455,
  "image_path": "images/image_002455.png",
  "num_objects": 3,
  "objects": [
    {
      "shape": "triangle",
      "color": [
        255,
        0,
        0
      ],
      "bbox": [
        42,
        30,
        53,
        41
      ],
      "center": [
        47,
        35
      ],
      "size": [
        11,
        11
      ],
      "area": 121
    },
    {
      "shape": "triangle",
      "color": [
        0,
        255,
        255
      ],
      "bbox": [
        1,
        4,
        13,
        16
      ],
      "center": [
        7,
        10
      ],
      "size": [
        12,
        12
      ],
      "area": 144
    },
    {
      "shape": "square",
      "color": [
        255,
        128,
        0
      ],
      "bbox": [
        31,
        33,
        46,
        48
      ],
      "center": [
        38,
        40
      ],
      "size": [
        15,
        15
      ],
      "area": 225
    }
  ]
}