{
  "image_id": 5787,
  "image_path": "images/image_005787.png",
  "num_objects": 3,
  "objects": [
    {
      "shape": "square",
      "color": [
        128,
        0,
        255
      ],
      "bbox": [
        33,
        34,
        54,
        55
      ],
      "center": [
        43,
        44
      ],
      "size": [
        21,
        21
      ],
      "area": 441
    },
    {
      "shape": "circle",
      "color": [
        0,
        255,
        0
      ],
      "bbox": [
        4,
        1,
        18,
        15
      ],
      "center": [
        11,
        8
      ],
      "size": [
        14,
        14
      ],
      "area": 196
    },
    {
      "shape": "circle",
      "color": [
        255,
        128,
        0
      ],
      "bbox": [
        34,
        19,
        53,
        38
      ],
      "center": [
        43,
        28
      ],
      "size": [
        19,
        19
      ],
      "area": 361
    }
  ]
}