{
  "image_id": 7913,
  "image_path": "images/image_007913.png",
  "num_objects": 4,
  "objects": [
    {
      "shape": "triangle",
      "color": [
        255,
        128,
        0
      ],
      "bbox": [
        45,
        23,
        60,
        38
      ],
      "center": [
        52,
        30
      ],
      "size": [
        15,
        15
      ],
      "area": 225
    },
    {
      "shape": "triangle",
      "color": [
        255,
        0,
        255
      ],
      "bbox": [
        40,
        19,
        57,
        36
      ],
      "center": [
        48,
        27
      ],
      "size": [
        17,
        17
      ],
      "area": 289
    },
    {
      "shape": "triangle",
      "color": [
        128,
        0,
        255
      ],
      "bbox": [
        48,
        7,
        63,
        22
      ],
      "center": [
        55,
        14
      ],
      "size": [
        15,
        15
      ],
      "area": 225
    },
    {
      "shape": "circle",
      "color": [
        0,
        255,
        0
      ],
      "bbox": [
        33,
        34,
        46,
        47
      ],
      "center": [
        39,
        40
      ],
      "size": [
        13,
        13
      ],
      "area": 169
    }
  ]
}