{
  "image_id": 1259,
  "image_path": "images/image_001259.png",
  "num_objects": 3,
  "objects": [
    {
      "shape": "circle",
      "color": [
        255,
        0,
        0
      ],
      "bbox": [
        20,
        47,
        35,
        62
      ],
      "center": [
        27,
        54
      ],
      "size": [
        15,
        15
      ],
      "area": 225
    },
    {
      "shape": "square",
      "color": [
        0,
        255,
        255
      ],
      "bbox": [
        31,
        7,
        43,
        19
      ],
      "center": [
        37,
        13
      ],
      "size": [
        12,
        12
      ],
      "area": 144
    },
    {
      "shape": "triangle",
      "color": [
        255,
        255,
        0
      ],
      "bbox": [
        3,
        35,
        24,
        56
      ],
      "center": [
        13,
        45
      ],
      "size": [
        21,
        21
      ],
      "area": 441
    }
  ]
}