{
  "image_id": 3666,
  "image_path": "images/image_003666.png",
  "num_objects": 3,
  "objects": [
    {
      "shape": "square",
      "color": [
        255,
        128,
        0
      ],
      "bbox": [
        5,
        42,
        17,
        54
      ],
      "center": [
        11,
        48
      ],
      "size": [
        12,
        12
      ],
      "area": 144
    },
    {
      "shape": "square",
      "color": [
        128,
        0,
        255
      ],
      "bbox": [
        42,
        33,
        64,
        55
      ],
      "center": [
        53,
        44
      ],
      "size": [
        22,
        22
      ],
      "area": 484
    },
    {
      "shape": "triangle",
      "color": [
        0,
        0,
        255
      ],
      "bbox": [
        2,
        43,
        21,
        62
      ],
      "center": [
        11,
        52
      ],
      "size": [
        19,
        19
      ],
      "area": 361
    }
  ]
}