{
  "image_id": 3624,
  "image_path": "images/image_003624.png",
  "num_objects": 4,
  "objects": [
    {
      "shape": "triangle",
      "color": [
        128,
        0,
        255
      ],
      "bbox": [
        13,
        28,
        33,
        48
      ],
      "center": [
        23,
        38
      ],
      "size": [
        20,
        20
      ],
      "area": 400
    },
    {
      "shape": "square",
      "color": [
        255,
        255,
        0
      ],
      "bbox": [
        3,
        47,
        18,
        62
      ],
      "center": [
        10,
        54
      ],
      "size": [
        15,
        15
      ],
      "area": 225
    },
    {
      "shape": "square",
      "color": [
        128,
        0,
        255
      ],
      "bbox": [
        43,
        44,
        62,
        63
      ],
      "center": [
        52,
        53
      ],
      "size": [
        19,
        19
      ],
      "area": 361
    },
    {
      "shape": "square",
      "color": [
        255,
        255,
        0
      ],
      "bbox": [
        1,
        9,
        13,
        21
      ],
      "center": [
        7,
        15
      ],
      "size": [
        12,
        12
      ],
      "area": 144
    }
  ]
}