{
  "image_id": 2446,
  "image_path": "images/image_002446.png",
  "num_objects": 3,
  "objects": [
    {
      "shape": "square",
      "color": [
        255,
        255,
        0
      ],
      "bbox": [
        23,
        9,
        44,
        30
      ],
      "center": [
        33,
        19
      ],
      "size": [
        21,
        21
      ],
      "area": 441
    },
    {
      "shape": "circle",
      "color": [
        255,
        0,
        255
      ],
      "bbox": [
        22,
        43,
        36,
        57
      ],
      "center": [
        29,
        50
      ],
      "size": [
        14,
        14
      ],
      "area": 196
    },
    {
      "shape": "circle",
      "color": [
        255,
        0,
        255
      ],
      "bbox": [
        51,
        16,
        61,
        26
      ],
      "center": [
        56,
        21
      ],
      "size": [
        10,
        10
      ],
      "area": 100
    }
  ]
}