{
  "image_id": 1164,
  "image_path": "images/image_001164.png",
  "num_objects": 3,
  "objects": [
    {
      "shape": "circle",
      "color": [
        255,
        0,
        0
      ],
      "bbox": [
        19,
        18,
        38,
        37
      ],
      "center": [
        28,
        27
      ],
      "size": [
        19,
        19
      ],
      "area": 361
    },
    {
      "shape": "circle",
      "color": [
        255,
        0,
        0
      ],
      "bbox": [
        15,
        1,
        26,
        12
      ],
      "center": [
        20,
        6
      ],
      "size": [
        11,
        11
      ],
      "area": 121
    },
    {
      "shape": "circle",
      "color": [
        255,
        0,
        0
      ],
      "bbox": [
        16,
        27,
        35,
        46
      ],
      "center": [
        25,
        36
      ],
      "size": [
        19,
        19
      ],
      "area": 361
    }
  ]
}