{
  "image_id": 569,
  "image_path": "images/image_000569.png",
  "num_objects": 4,
  "objects": [
    {
      "shape": "circle",
      "color": [
        0,
        255,
        255
      ],
      "bbox": [
        22,
        40,
        44,
        62
      ],
      "center": [
        33,
        51
      ],
      "size": [
        22,
        22
      ],
      "area": 484
    },
    {
      "shape": "circle",
      "color": [
        128,
        0,
        255
      ],
      "bbox": [
        39,
        29,
        55,
        45
      ],
      "center": [
        47,
        37
      ],
      "size": [
        16,
        16
      ],
      "area": 256
    },
    {
      "shape": "circle",
      "color": [
        255,
        255,
        0
      ],
      "bbox": [
        40,
        39,
        56,
        55
      ],
      "center": [
        48,
        47
      ],
      "size": [
        16,
        16
      ],
      "area": 256
    },
    {
      "shape": "circle",
      "color": [
        0,
        255,
        0
      ],
      "bbox": [
        8,
        5,
        28,
        25
      ],
      "center": [
        18,
        15
      ],
      "size": [
        20,
        20
      ],
      "area": 400
    }
  ]
}