{
  "image_id": 7311,
  "image_path": "images/image_007311.png",
  "num_objects": 3,
  "objects": [
    {
      "shape": "square",
      "color": [
        255,
        255,
        0
      ],
      "bbox": [
        14,
        13,
        36,
        35
      ],
      "center": [
        25,
        24
      ],
      "size": [
        22,
        22
      ],
      "area": 484
    },
    {
      "shape": "triangle",
      "color": [
        0,
        0,
        255
      ],
      "bbox": [
        15,
        16,
        33,
        34
      ],
      "center": [
        24,
        25
      ],
      "size": [
        18,
        18
      ],
      "area": 324
    },
    {
      "shape": "square",
      "color": [
        255,
        0,
        0
      ],
      "bbox": [
        42,
        47,
        57,
        62
      ],
      "center": [
        49,
        54
      ],
      "size": [
        15,
        15
      ],
      "area": 225
    }
  ]
}