{
  "image_id": 480,
  "image_path": "images/image_000480.png",
  "num_objects": 2,
  "objects": [
    {
      "shape": "circle",
      "color": [
        0,
        0,
        255
      ],
      "bbox": [
        49,
        39,
        61,
        51
      ],
      "center": [
        55,
        45
      ],
      "size": [
        12,
        12
      ],
      "area": 144
    },
    {
      "shape": "circle",
      "color": [
        0,
        0,
        255
      ],
      "bbox": [
        34,
        33,
        52,
        51
      ],
      "center": [
        43,
        42
      ],
      "size": [
        18,
        18
      ],
      "area": 324
    }
  ]
}