{
  "image_id": 6455,
  "image_path": "images/image_006455.png",
  "num_objects": 3,
  "objects": [
    {
      "shape": "square",
      "color": [
        0,
        255,
        0
      ],
      "bbox": [
        29,
        32,
        39,
        42
      ],
      "center": [
        34,
        37
      ],
      "size": [
        10,
        10
      ],
      "area": 100
    },
    {
      "shape": "triangle",
      "color": [
        0,
        0,
        255
      ],
      "bbox": [
        50,
        40,
        64,
        54
      ],
      "center": [
        57,
        47
      ],
      "size": [
        14,
        14
      ],
      "area": 196
    },
    {
      "shape": "square",
      "color": [
        255,
        255,
        0
      ],
      "bbox": [
        36,
        5,
        56,
        25
      ],
      "center": [
        46,
        15
      ],
      "size": [
        20,
        20
      ],
      "area": 400
    }
  ]
}