{
  "image_id": 4876,
  "image_path": "images/image_004876.png",
  "num_objects": 4,
  "objects": [
    {
      "shape": "triangle",
      "color": [
        255,
        0,
        255
      ],
      "bbox": [
        30,
        15,
        47,
        32
      ],
      "center": [
        38,
        23
      ],
      "size": [
        17,
        17
      ],
      "area": 289
    },
    {
      "shape": "square",
      "color": [
        255,
        128,
        0
      ],
      "bbox": [
        34,
        47,
        51,
        64
      ],
      "center": [
        42,
        55
      ],
      "size": [
        17,
        17
      ],
      "area": 289
    },
    {
      "shape": "circle",
      "color": [
        0,
        0,
        255
      ],
      "bbox": [
        20,
        4,
        37,
        21
      ],
      "center": [
        28,
        12
      ],
      "size": [
        17,
        17
      ],
      "area": 289
    },
    {
      "shape": "square",
      "color": [
        255,
        0,
        0
      ],
      "bbox": [
        19,
        33,
        38,
        52
      ],
      "center": [
        28,
        42
      ],
      "size": [
        19,
        19
      ],
      "area": 361
    }
  ]
}