{
  "image_id": 5785,
  "image_path": "images/image_005785.png",
  "num_objects": 2,
  "objects": [
    {
      "shape": "triangle",
      "color": [
        255,
        0,
        255
      ],
      "bbox": [
        7,
        29,
        18,
        40
      ],
      "center": [
        12,
        34
      ],
      "size": [
        11,
        11
      ],
      "area": 121
    },
    {
      "shape": "circle",
      "color": [
        128,
        0,
        255
      ],
      "bbox": [
        17,
        18,
        28,
        29
      ],
      "center": [
        22,
        23
      ],
      "size": [
        11,
        11
      ],
      "area": 121
    }
  ]
}