{
  "image_id": 3213,
  "image_path": "images/image_003213.png",
  "num_objects": 2,
  "objects": [
    {
      "shape": "square",
      "color": [
        0,
        255,
        255
      ],
      "bbox": [
        1,
        28,
        12,
        39
      ],
      "center": [
        6,
        33
      ],
      "size": [
        11,
        11
      ],
      "area": 121
    },
    {
      "shape": "triangle",
      "color": [
        255,
        0,
        255
      ],
      "bbox": [
        23,
        50,
        34,
        61
      ],
      "center": [
        28,
        55
      ],
      "size": [
        11,
        11
      ],
      "area": 121
    }
  ]
}