{
  "image_id": 2616,
  "image_path": "images/image_002616.png",
  "num_objects": 2,
  "objects": [
    {
      "shape": "square",
      "color": [
        255,
        0,
        255
      ],
      "bbox": [
        11,
        42,
        26,
        57
      ],
      "center": [
        18,
        49
      ],
      "size": [
        15,
        15
      ],
      "area": 225
    },
    {
      "shape": "square",
      "color": [
        255,
        0,
        255
      ],
      "bbox": [
        20,
        26,
        33,
        39
      ],
      "center": [
        26,
        32
      ],
      "size": [
        13,
        13
      ],
      "area": 169
    }
  ]
}