{
  "image_id": 3915,
  "image_path": "images/image_003915.png",
  "num_objects": 4,
  "objects": [
    {
      "shape": "triangle",
      "color": [
        255,
        128,
        0
      ],
      "bbox": [
        24,
        8,
        37,
        21
      ],
      "center": [
        30,
        14
      ],
      "size": [
        13,
        13
      ],
      "area": 169
    },
    {
      "shape": "circle",
      "color": [
        255,
        128,
        0
      ],
      "bbox": [
        34,
        22,
        53,
        41
      ],
      "center": [
        43,
        31
      ],
      "size": [
        19,
        19
      ],
      "area": 361
    },
    {
      "shape": "triangle",
      "color": [
        255,
        0,
        0
      ],
      "bbox": [
        33,
        49,
        45,
        61
      ],
      "center": [
        39,
        55
      ],
      "size": [
        12,
        12
      ],
      "area": 144
    },
    {
      "shape": "circle",
      "color": [
        0,
        0,
        255
      ],
      "bbox": [
        33,
        9,
        49,
        25
      ],
      "center": [
        41,
        17
      ],
      "size": [
        16,
        16
      ],
      "area": 256
    }
  ]
}