{
  "image_id": 3568,
  "image_path": "images/image_003568.png",
  "num_objects": 2,
  "objects": [
    {
      "shape": "circle",
      "color": [
        128,
        0,
        255
      ],
      "bbox": [
        45,
        33,
        57,
        45
      ],
      "center": [
        51,
        39
      ],
      "size": [
        12,
        12
      ],
      "area": 144
    },
    {
      "shape": "square",
      "color": [
        0,
        0,
        255
      ],
      "bbox": [
        8,
        39,
        27,
        58
      ],
      "center": [
        17,
        48
      ],
      "size": [
        19,
        19
      ],
      "area": 361
    }
  ]
}