{
  "image_id": 386,
  "image_path": "images/image_000386.png",
  "num_objects": 3,
  "objects": [
    {
      "shape": "circle",
      "color": [
        255,
        0,
        255
      ],
      "bbox": [
        33,
        28,
        53,
        48
      ],
      "center": [
        43,
        38
      ],
      "size": [
        20,
        20
      ],
      "area": 400
    },
    {
      "shape": "square",
      "color": [
        128,
        0,
        255
      ],
      "bbox": [
        34,
        6,
        55,
        27
      ],
      "center": [
        44,
        16
      ],
      "size": [
        21,
        21
      ],
      "area": 441
    },
    {
      "shape": "triangle",
      "color": [
        0,
        0,
        255
      ],
      "bbox": [
        38,
        24,
        57,
        43
      ],
      "center": [
        47,
        33
      ],
      "size": [
        19,
        19
      ],
      "area": 361
    }
  ]
}