{
  "image_id": 7711,
  "image_path": "images/image_007711.png",
  "num_objects": 4,
  "objects": [
    {
      "shape": "square",
      "color": [
        0,
        0,
        255
      ],
      "bbox": [
        44,
        32,
        62,
        50
      ],
      "center": [
        53,
        41
      ],
      "size": [
        18,
        18
      ],
      "area": 324
    },
    {
      "shape": "circle",
      "color": [
        0,
        255,
        0
      ],
      "bbox": [
        30,
        42,
        46,
        58
      ],
      "center": [
        38,
        50
      ],
      "size": [
        16,
        16
      ],
      "area": 256
    },
    {
      "shape": "square",
      "color": [
        0,
        255,
        0
      ],
      "bbox": [
        9,
        46,
        23,
        60
      ],
      "center": [
        16,
        53
      ],
      "size": [
        14,
        14
      ],
      "area": 196
    },
    {
      "shape": "triangle",
      "color": [
        0,
        0,
        255
      ],
      "bbox": [
        41,
        27,
        53,
        39
      ],
      "center": [
        47,
        33
      ],
      "size": [
        12,
        12
      ],
      "area": 144
    }
  ]
}