{
  "image_id": 6582,
  "image_path": "images/image_006582.png",
  "num_objects": 3,
  "objects": [
    {
      "shape": "square",
      "color": [
        255,
        128,
        0
      ],
      "bbox": [
        30,
        8,
        41,
        19
      ],
      "center": [
        35,
        13
      ],
      "size": [
        11,
        11
      ],
      "area": 121
    },
    {
      "shape": "circle",
      "color": [
        255,
        128,
        0
      ],
      "bbox": [
        11,
        38,
        32,
        59
      ],
      "center": [
        21,
        48
      ],
      "size": [
        21,
        21
      ],
      "area": 441
    },
    {
      "shape": "triangle",
      "color": [
        0,
        255,
        255
      ],
      "bbox": [
        9,
        17,
        19,
        27
      ],
      "center": [
        14,
        22
      ],
      "size": [
        10,
        10
      ],
      "area": 100
    }
  ]
}