{
  "image_id": 5940,
  "image_path": "images/image_005940.png",
  "num_objects": 3,
  "objects": [
    {
      "shape": "triangle",
      "color": [
        128,
        0,
        255
      ],
      "bbox": [
        38,
        35,
        55,
        52
      ],
      "center": [
        46,
        43
      ],
      "size": [
        17,
        17
      ],
      "area": 289
    },
    {
      "shape": "triangle",
      "color": [
        0,
        255,
        0
      ],
      "bbox": [
        22,
        18,
        41,
        37
      ],
      "center": [
        31,
        27
      ],
      "size": [
        19,
        19
      ],
      "area": 361
    },
    {
      "shape": "circle",
      "color": [
        128,
        0,
        255
      ],
      "bbox": [
        0,
        35,
        13,
        48
      ],
      "center": [
        6,
        41
      ],
      "size": [
        13,
        13
      ],
      "area": 169
    }
  ]
}