{
  "image_id": 7585,
  "image_path": "images/image_007585.png",
  "num_objects": 4,
  "objects": [
    {
      "shape": "circle",
      "color": [
        0,
        0,
        255
      ],
      "bbox": [
        17,
        45,
        30,
        58
      ],
      "center": [
        23,
        51
      ],
      "size": [
        13,
        13
      ],
      "area": 169
    },
    {
      "shape": "circle",
      "color": [
        255,
        0,
        255
      ],
      "bbox": [
        7,
        9,
        28,
        30
      ],
      "center": [
        17,
        19
      ],
      "size": [
        21,
        21
      ],
      "area": 441
    },
    {
      "shape": "square",
      "color": [
        255,
        0,
        0
      ],
      "bbox": [
        22,
        39,
        43,
        60
      ],
      "center": [
        32,
        49
      ],
      "size": [
        21,
        21
      ],
      "area": 441
    },
    {
      "shape": "triangle",
      "color": [
        0,
        255,
        0
      ],
      "bbox": [
        43,
        18,
        62,
        37
      ],
      "center": [
        52,
        27
      ],
      "size": [
        19,
        19
      ],
      "area": 361
    }
  ]
}