{
  "image_id": 4937,
  "image_path": "images/image_004937.png",
  "num_objects": 4,
  "objects": [
    {
      "shape": "square",
      "color": [
        255,
        128,
        0
      ],
      "bbox": [
        21,
        41,
        37,
        57
      ],
      "center": [
        29,
        49
      ],
      "size": [
        16,
        16
      ],
      "area": 256
    },
    {
      "shape": "circle",
      "color": [
        255,
        255,
        0
      ],
      "bbox": [
        9,
        13,
        27,
        31
      ],
      "center": [
        18,
        22
      ],
      "size": [
        18,
        18
      ],
      "area": 324
    },
    {
      "shape": "circle",
      "color": [
        255,
        0,
        0
      ],
      "bbox": [
        24,
        27,
        33,
        36
      ],
      "center": [
        28,
        31
      ],
      "size": [
        9,
        9
      ],
      "area": 81
    },
    {
      "shape": "circle",
      "color": [
        255,
        255,
        0
      ],
      "bbox": [
        50,
        5,
        62,
        17
      ],
      "center": [
        56,
        11
      ],
      "size": [
        12,
        12
      ],
      "area": 144
    }
  ]
}