{
  "image_id": 4326,
  "image_path": "images/image_004326.png",
  "num_objects": 3,
  "objects": [
    {
      "shape": "square",
      "color": [
        0,
        255,
        255
      ],
      "bbox": [
        4,
        19,
        19,
        34
      ],
      "center": [
        11,
        26
      ],
      "size": [
        15,
        15
      ],
      "area": 225
    },
    {
      "shape": "square",
      "color": [
        0,
        255,
        255
      ],
      "bbox": [
        6,
        49,
        19,
        62
      ],
      "center": [
        12,
        55
      ],
      "size": [
        13,
        13
      ],
      "area": 169
    },
    {
      "shape": "circle",
      "color": [
        0,
        255,
        0
      ],
      "bbox": [
        30,
        32,
        51,
        53
      ],
      "center": [
        40,
        42
      ],
      "size": [
        21,
        21
      ],
      "area": 441
    }
  ]
}