{
  "image_id": 6222,
  "image_path": "images/image_006222.png",
  "num_objects": 4,
  "objects": [
    {
      "shape": "square",
      "color": [
        128,
        0,
        255
      ],
      "bbox": [
        5,
        26,
        19,
        40
      ],
      "center": [
        12,
        33
      ],
      "size": [
        14,
        14
      ],
      "area": 196
    },
    {
      "shape": "triangle",
      "color": [
        128,
        0,
        255
      ],
      "bbox": [
        18,
        39,
        35,
        56
      ],
      "center": [
        26,
        47
      ],
      "size": [
        17,
        17
      ],
      "area": 289
    },
    {
      "shape": "triangle",
      "color": [
        0,
        255,
        255
      ],
      "bbox": [
        13,
        12,
        26,
        25
      ],
      "center": [
        19,
        18
      ],
      "size": [
        13,
        13
      ],
      "area": 169
    },
    {
      "shape": "square",
      "color": [
        255,
        0,
        0
      ],
      "bbox": [
        40,
        42,
        58,
        60
      ],
      "center": [
        49,
        51
      ],
      "size": [
        18,
        18
      ],
      "area": 324
    }
  ]
}