{
  "image_id": 3263,
  "image_path": "images/image_003263.png",
  "num_objects": 4,
  "objects": [
    {
      "shape": "square",
      "color": [
        0,
        255,
        255
      ],
      "bbox": [
        52,
        14,
        63,
        25
      ],
      "center": [
        57,
        19
      ],
      "size": [
        11,
        11
      ],
      "area": 121
    },
    {
      "shape": "circle",
      "color": [
        255,
        0,
        255
      ],
      "bbox": [
        33,
        12,
        54,
        33
      ],
      "center": [
        43,
        22
      ],
      "size": [
        21,
        21
      ],
      "area": 441
    },
    {
      "shape": "triangle",
      "color": [
        0,
        0,
        255
      ],
      "bbox": [
        15,
        7,
        26,
        18
      ],
      "center": [
        20,
        12
      ],
      "size": [
        11,
        11
      ],
      "area": 121
    },
    {
      "shape": "circle",
      "color": [
        255,
        128,
        0
      ],
      "bbox": [
        10,
        46,
        25,
        61
      ],
      "center": [
        17,
        53
      ],
      "size": [
        15,
        15
      ],
      "area": 225
    }
  ]
}