{
  "image_id": 7305,
  "image_path": "images/image_007305.png",
  "num_objects": 3,
  "objects": [
    {
      "shape": "square",
      "color": [
        0,
        255,
        255
      ],
      "bbox": [
        32,
        21,
        44,
        33
      ],
      "center": [
        38,
        27
      ],
      "size": [
        12,
        12
      ],
      "area": 144
    },
    {
      "shape": "triangle",
      "color": [
        255,
        0,
        255
      ],
      "bbox": [
        39,
        13,
        55,
        29
      ],
      "center": [
        47,
        21
      ],
      "size": [
        16,
        16
      ],
      "area": 256
    },
    {
      "shape": "square",
      "color": [
        255,
        128,
        0
      ],
      "bbox": [
        27,
        2,
        45,
        20
      ],
      "center": [
        36,
        11
      ],
      "size": [
        18,
        18
      ],
      "area": 324
    }
  ]
}