{
  "image_id": 5737,
  "image_path": "images/image_005737.png",
  "num_objects": 4,
  "objects": [
    {
      "shape": "circle",
      "color": [
        0,
        255,
        255
      ],
      "bbox": [
        12,
        29,
        28,
        45
      ],
      "center": [
        20,
        37
      ],
      "size": [
        16,
        16
      ],
      "area": 256
    },
    {
      "shape": "square",
      "color": [
        128,
        0,
        255
      ],
      "bbox": [
        37,
        11,
        54,
        28
      ],
      "center": [
        45,
        19
      ],
      "size": [
        17,
        17
      ],
      "area": 289
    },
    {
      "shape": "circle",
      "color": [
        255,
        0,
        255
      ],
      "bbox": [
        31,
        26,
        50,
        45
      ],
      "center": [
        40,
        35
      ],
      "size": [
        19,
        19
      ],
      "area": 361
    },
    {
      "shape": "circle",
      "color": [
        255,
        128,
        0
      ],
      "bbox": [
        2,
        7,
        22,
        27
      ],
      "center": [
        12,
        17
      ],
      "size": [
        20,
        20
      ],
      "area": 400
    }
  ]
}